math_evaluate/__init__.py
math_evaluate/cli.py
math_evaluate/evaluator.py
math_evaluate/main.py
math_evaluate-0.1.6.dist-info/licenses/LICENSE
math_evaluate-0.1.6.dist-info/METADATA
math_evaluate-0.1.6.dist-info/WHEEL
math_evaluate-0.1.6.dist-info/entry_points.txt
math_evaluate-0.1.6.dist-info/top_level.txt
math_evaluate-0.1.6.dist-info/RECORD
