Metadata-Version: 2.4
Name: math-evaluate
Version: 0.1.6
Summary: A simple CLI calculator for quick math.
Author: mhasanali2010
License-Expression: MIT
Classifier: Programming Language :: Python :: 3
Classifier: Operating System :: OS Independent
Requires-Python: >=3.10
License-File: LICENSE
Dynamic: license-file
